{"ID":31190,"Author":{"Name":"BinaryBrewWorks","ID":0,"FullName":"","Gravatar":"ffc3f2c78dcb99abf76f6bcb6b1b10b3"},"Title":"Kali A Day #02 || dnsrecon","Description":"\u003cdiv class=\"content\"\u003e\u003cp\u003eKali A Day #02\u003cbr/\u003e\nPresented By Binary Brew Works\u003c/p\u003e\n\n\u003cp\u003eToday\u0026#39;s tool is \u0026#39;dnsrecon\u0026#39; because DNS is awesomesauce.\u003cbr/\u003e\nWritten by \u003cbr/\u003e\nCarlos Perez\u003cbr/\u003e\nDarkoperator\u003c/p\u003e\n\n\u003cp\u003e\u003ca href=\"https://twitter.com/carlos_perez\"\u003ehttps://twitter.com/carlos_perez\u003c/a\u003e\u003cbr/\u003e\n\u003ca href=\"https://github.com/darkoperator/dnsrecon\"\u003ehttps://github.com/darkoperator/dnsrecon\u003c/a\u003e\u003cbr/\u003e\n\u003ca href=\"http://www.darkoperator.com/\"\u003ehttp://www.darkoperator.com/\u003c/a\u003e\u003c/p\u003e\n\n\u003cp\u003eKali A Day is a short overview of a Kali Linux tool...wait for it...every day.  For more follow Binary Brew Works at:\u003c/p\u003e\n\n\u003cp\u003eTwitter:  @10101_Brew\u003cbr/\u003e\n\u003ca href=\"http://www.10101Brew.com\"\u003ehttp://www.10101Brew.com\u003c/a\u003e\u003c/p\u003e\n\u003c/div\u003e","Time":"2015-12-04T15:37:35Z","Tags":["Linux","bash","xterm"]}