{
  "version": 1,
  "width": 80,
  "height": 34,
  "duration": 38.986305,
  "command": "/bin/bash",
  "title": "",
  "env": {
    "TERM": "xterm-256color",
    "SHELL": "/bin/bash"
  },
  "stdout": [
    [
      0.065368,
      "\u001b]0;root@rautasorsa:~\u0007"
    ],
    [
      0.001616,
      "[root@rautasorsa ~]# "
    ],
    [
      0.589207,
      "e"
    ],
    [
      0.288028,
      "2"
    ],
    [
      0.303870,
      "l"
    ],
    [
      0.087994,
      "a"
    ],
    [
      0.208096,
      "b"
    ],
    [
      0.039779,
      "e"
    ],
    [
      0.143971,
      "l"
    ],
    [
      0.112100,
      " "
    ],
    [
      0.296000,
      "/"
    ],
    [
      0.151959,
      "d"
    ],
    [
      0.056107,
      "e"
    ],
    [
      0.223939,
      "v"
    ],
    [
      0.378614,
      "/"
    ],
    [
      0.221528,
      "s"
    ],
    [
      0.208052,
      "d"
    ],
    [
      0.215928,
      "c"
    ],
    [
      0.288048,
      "1"
    ],
    [
      0.999981,
      "\r\n"
    ],
    [
      0.002254,
      "backup_disk\r\n"
    ],
    [
      0.000455,
      "\u001b]0;root@rautasorsa:~\u0007"
    ],
    [
      0.000082,
      "[root@rautasorsa ~]# "
    ],
    [
      4.533523,
      "e"
    ],
    [
      0.367915,
      "2"
    ],
    [
      0.456029,
      "l"
    ],
    [
      0.104023,
      "a"
    ],
    [
      0.295978,
      "b"
    ],
    [
      0.039935,
      "e"
    ],
    [
      0.128034,
      "l"
    ],
    [
      0.256036,
      " "
    ],
    [
      0.448211,
      "/"
    ],
    [
      0.183732,
      "d"
    ],
    [
      0.056240,
      "e"
    ],
    [
      0.263929,
      "v"
    ],
    [
      0.472055,
      "/"
    ],
    [
      0.359940,
      "s"
    ],
    [
      0.200036,
      "d"
    ],
    [
      0.231961,
      "c"
    ],
    [
      0.304064,
      "1"
    ],
    [
      0.664037,
      " "
    ],
    [
      0.255973,
      "b"
    ],
    [
      0.208044,
      "a"
    ],
    [
      0.087983,
      "c"
    ],
    [
      0.103999,
      "k"
    ],
    [
      0.215986,
      "u"
    ],
    [
      0.215956,
      "p"
    ],
    [
      0.400260,
      "_"
    ],
    [
      0.287843,
      "d"
    ],
    [
      0.112042,
      "i"
    ],
    [
      0.135972,
      "s"
    ],
    [
      0.120042,
      "k"
    ],
    [
      0.367959,
      "\r\n"
    ],
    [
      5.438707,
      "\u001b]0;root@rautasorsa:~\u0007[root@rautasorsa ~]# "
    ],
    [
      2.537874,
      "v"
    ],
    [
      0.095780,
      "i"
    ],
    [
      0.095868,
      " "
    ],
    [
      0.240011,
      "/"
    ],
    [
      0.544297,
      "e"
    ],
    [
      0.207871,
      "t"
    ],
    [
      0.264089,
      "c"
    ],
    [
      0.527969,
      "/"
    ],
    [
      0.263951,
      "f"
    ],
    [
      0.288137,
      "s"
    ],
    [
      0.207966,
      "t"
    ],
    [
      0.175972,
      "a"
    ],
    [
      0.175886,
      "b"
    ],
    [
      1.008795,
      "\r\n"
    ],
    [
      0.003239,
      "\u001b[?1049h\u001b[?1h\u001b="
    ],
    [
      0.000353,
      "\u001b[1;34r\u001b[?12;25h\u001b[?12l\u001b[?25h\u001b[27m\u001b[m\u001b[H\u001b[2J\u001b[?25l\u001b[34;1H\"/etc/fstab\""
    ],
    [
      0.000029,
      " 11L, 577C"
    ],
    [
      0.000072,
      "\u001b[1;1HLABEL=root-hmanzgva    /\u001b[9Cext3     defaults   1  1\r\n/var/swap/swap.001\u001b[10Cswap      swap   defaults   0  0\r\nnone\u001b[8C/dev/pts  devpts defaults   0  0\r\nnone\u001b[8C/dev/shm  tmpfs  defaults   0  0\r\nnone\u001b[8C/proc     proc   defaults   0  0\r\nnone\u001b[8C/sys      sysfs  defaults   0  0\r\nnone\u001b[8C/sys/fs/cgroup cgroup memory 0 0\r\n/opt/xensource/packages/iso/XenCenter.iso   /var/xen/xc-install   iso9660   loopp\u001b[9;1H,ro   0  0\r\n/dev/sdb1   /mnt/data ext3   defaults   0  1\r\n#/dev/sdc1   /mnt/backup ext3   defaults   0  1\r\nLABEL=backup_disk /mnt/backup ext3 defaults 0 0\r\n\u001b[94m~                                                                               \u001b[14;1H~                                                                               \u001b[15;1H~                                                                               \u001b[16;1H~                                                                               \u001b[17;1H~                                                                               \u001b[18;1H~                                                                               \u001b[19;1H~                                                                               \u001b[20;1H~                                                                               \u001b[21;1H~                                                                               \u001b[22;1H~                                                                               \u001b[23;1H~                                                                               \u001b[24;1H~                                                                               \u001b[25;1H~                                                                               \u001b[26;1H~                                                                               \u001b[27;1H~                                                                               \u001b[28;1H~                                                                               \u001b[29;1H~                                                                               "
    ],
    [
      0.000020,
      "\u001b[30;1H~                                                                               \u001b[31;1H~                                                                               \u001b[32;1H~                                                                               \u001b[33;1H~                                                                               \u001b[1;1H\u001b[?12l\u001b[?25h"
    ],
    [
      1.740011,
      "\u001b[12;1H"
    ],
    [
      0.799944,
      "\u001b[?25l\u001b[m\u001b[34;1H\u001b[1m-- INSERT --\u001b[m\u001b[34;14H\u001b[K\u001b[12;1H\u001b[?12l\u001b[?25h"
    ],
    [
      0.408105,
      "\u001b[?25l-LABEL=backup_disk /mnt/backup ext3 defaults 0 0\r-\u001b[?12l\u001b[?25h"
    ],
    [
      0.135787,
      "\u001b[?25l-LABEL=backup_disk /mnt/backup ext3 defaults 0 0\r--\u001b[?12l\u001b[?25h"
    ],
    [
      0.272001,
      "\u001b[?25l\u003eLABEL=backup_disk /mnt/backup ext3 defaults 0 0\r--\u003e\u001b[?12l\u001b[?25h"
    ],
    [
      0.977400,
      "\u001b[34;1H\u001b[K\u001b[12;3H"
    ],
    [
      0.598772,
      "\u001b[?25l\u001b[?12l\u001b[?25h\u0008"
    ],
    [
      0.183817,
      "\u0008"
    ],
    [
      0.175993,
      "\u0007"
    ],
    [
      0.504232,
      "\u001b[?25l-\u003eLABEL=backup_disk /mnt/backup ext3 defaults 0 0 \r\u001b[?12l\u001b[?25h"
    ],
    [
      0.255918,
      "\u001b[?25l\u003eLABEL=backup_disk /mnt/backup ext3 defaults 0 0 \r\u001b[?12l\u001b[?25h"
    ],
    [
      0.335903,
      "\u001b[?25lLABEL=backup_disk /mnt/backup ext3 defaults 0 0 \r\u001b[?12l\u001b[?25h"
    ],
    [
      0.728137,
      "\u001b[?25l\u001b[34;1H:\u001b[?12l\u001b[?25h"
    ],
    [
      0.240030,
      "w"
    ],
    [
      0.055938,
      "q"
    ],
    [
      0.552033,
      "!"
    ],
    [
      0.696352,
      "\r\u001b[?25l\"/etc/fstab\""
    ],
    [
      0.002882,
      " 11L, 577C written\r\r\r\n\u001b[?1l\u001b\u003e\u001b[?12l\u001b[?25h\u001b[?1049l"
    ],
    [
      0.000320,
      "\u001b]0;root@rautasorsa:~\u0007[root@rautasorsa ~]# "
    ],
    [
      0.740647,
      "e"
    ],
    [
      0.199982,
      "x"
    ],
    [
      0.087885,
      "i"
    ],
    [
      0.191984,
      "t"
    ],
    [
      0.264496,
      "\r\nexit\r\n"
    ]
  ]
}