{
  "version": 1,
  "width": 100,
  "height": 35,
  "duration": 60.733855,
  "command": "/bin/bash",
  "title": "Jails renaming",
  "env": {
    "TERM": "xterm",
    "SHELL": "/bin/bash"
  },
  "stdout": [
    [
      0.022618,
      "[root@1-test-dtrace-01x /]# "
    ],
    [
      1.217257,
      "c"
    ],
    [
      0.135923,
      "b"
    ],
    [
      0.079948,
      "s"
    ],
    [
      0.096008,
      "d"
    ],
    [
      0.056054,
      " "
    ],
    [
      0.087990,
      "j"
    ],
    [
      0.096043,
      "l"
    ],
    [
      0.087929,
      "s"
    ],
    [
      0.136007,
      "\r\n"
    ],
    [
      0.056748,
      "\u001b[1mJNAME     JID  IP4_ADDR     HOST_HOSTNAME   PATH                       STATUS\u001b[0m\r\n"
    ],
    [
      0.000004,
      "\u001b[0mtestjail  0    10.0.0.3/16  test.my.domain  /usr/jails/jails/testjail  Off\r\n"
    ],
    [
      0.000984,
      "[root@1-test-dtrace-01x /]# "
    ],
    [
      0.934231,
      "c"
    ],
    [
      0.127995,
      "b"
    ],
    [
      0.111956,
      "s"
    ],
    [
      0.079973,
      "d"
    ],
    [
      0.088017,
      " "
    ],
    [
      0.103848,
      "j"
    ],
    [
      0.192120,
      "r"
    ],
    [
      0.047951,
      "e"
    ],
    [
      0.104028,
      "n"
    ],
    [
      0.104011,
      "a"
    ],
    [
      0.088026,
      "m"
    ],
    [
      0.111980,
      "e"
    ],
    [
      0.111818,
      " "
    ],
    [
      0.096149,
      "-"
    ],
    [
      0.183966,
      "-"
    ],
    [
      0.232010,
      "h"
    ],
    [
      0.128012,
      "e"
    ],
    [
      0.232340,
      "l"
    ],
    [
      0.111616,
      "p"
    ],
    [
      0.208116,
      "\r\n"
    ],
    [
      0.025308,
      "[jail] Rename jail\r\n"
    ],
    [
      0.000003,
      "require: old new\r\nopt: host_hostname ip4_addr\r\n"
    ],
    [
      0.000017,
      "External help: http://www.bsdstore.ru/en/10.2.1a/wf_jrename.html\r\n"
    ],
    [
      0.000915,
      "[root@1-test-dtrace-01x /]# "
    ],
    [
      1.101559,
      "c"
    ],
    [
      0.151894,
      "b"
    ],
    [
      0.143965,
      "s"
    ],
    [
      0.071970,
      "d"
    ],
    [
      0.072054,
      " "
    ],
    [
      0.280111,
      "j"
    ],
    [
      0.319958,
      "r"
    ],
    [
      0.071840,
      "e"
    ],
    [
      0.088023,
      "n"
    ],
    [
      0.151965,
      "a"
    ],
    [
      0.056019,
      "m"
    ],
    [
      0.160092,
      "e"
    ],
    [
      0.111880,
      " "
    ],
    [
      0.311986,
      "o"
    ],
    [
      0.192010,
      "l"
    ],
    [
      0.048021,
      "d"
    ],
    [
      0.352056,
      "="
    ],
    [
      0.223877,
      "t"
    ],
    [
      0.055964,
      "e"
    ],
    [
      0.199979,
      "s"
    ],
    [
      0.143998,
      "t"
    ],
    [
      0.151822,
      "j"
    ],
    [
      0.064207,
      "a"
    ],
    [
      0.127724,
      "i"
    ],
    [
      0.200234,
      "l"
    ],
    [
      0.503714,
      " "
    ],
    [
      0.320246,
      "n"
    ],
    [
      0.111964,
      "e"
    ],
    [
      0.023773,
      "w"
    ],
    [
      0.376235,
      "="
    ],
    [
      0.943971,
      "j"
    ],
    [
      0.095687,
      "a"
    ],
    [
      0.280033,
      "l"
    ],
    [
      0.784179,
      "\u0008\u001b[K"
    ],
    [
      0.255704,
      "i"
    ],
    [
      0.216019,
      "l"
    ],
    [
      0.231946,
      "t"
    ],
    [
      0.032029,
      "e"
    ],
    [
      0.215956,
      "s"
    ],
    [
      0.191888,
      "t"
    ],
    [
      0.144004,
      "\r\n"
    ],
    [
      0.050956,
      "\u001b[0;35mRename\u001b[0m"
    ],
    [
      0.314206,
      "\u001b[0;35m.\u001b[0m"
    ],
    [
      5.457934,
      "\u001b[0;32mok\u001b[0m\r\n"
    ],
    [
      0.001081,
      "[root@1-test-dtrace-01x /]# "
    ],
    [
      7.623034,
      "c"
    ],
    [
      0.271803,
      "b"
    ],
    [
      0.143991,
      "s"
    ],
    [
      0.071998,
      "d"
    ],
    [
      0.088001,
      " "
    ],
    [
      0.039953,
      "j"
    ],
    [
      0.080030,
      "l"
    ],
    [
      0.111980,
      "s"
    ],
    [
      0.184037,
      "\r\n"
    ],
    [
      0.062629,
      "\u001b[1mJNAME     JID  IP4_ADDR     HOST_HOSTNAME   PATH                       STATUS\u001b[0m\r\n\u001b[0mjailtest  0    10.0.0.3/16  test.my.domain  /usr/jails/jails/jailtest  Off\r\n"
    ],
    [
      0.001024,
      "[root@1-test-dtrace-01x /]# "
    ],
    [
      1.944177,
      "c"
    ],
    [
      1.047966,
      "b"
    ],
    [
      0.055743,
      "s"
    ],
    [
      0.072038,
      "d"
    ],
    [
      0.047935,
      " "
    ],
    [
      0.135981,
      "j"
    ],
    [
      0.159992,
      "r"
    ],
    [
      0.056022,
      "e"
    ],
    [
      0.087992,
      "n"
    ],
    [
      0.135875,
      "a"
    ],
    [
      0.064151,
      "m"
    ],
    [
      0.127954,
      "e"
    ],
    [
      0.423995,
      " "
    ],
    [
      0.255826,
      "o"
    ],
    [
      0.200733,
      "l"
    ],
    [
      0.063266,
      "d"
    ],
    [
      0.560083,
      "="
    ],
    [
      0.520350,
      "j"
    ],
    [
      0.127441,
      "a"
    ],
    [
      0.071969,
      "i"
    ],
    [
      0.224028,
      "l"
    ],
    [
      0.560144,
      "t"
    ],
    [
      0.079817,
      "e"
    ],
    [
      0.208092,
      "s"
    ],
    [
      0.199884,
      "t"
    ],
    [
      0.047961,
      " "
    ],
    [
      0.463981,
      "n"
    ],
    [
      0.064015,
      "e"
    ],
    [
      0.055974,
      "w"
    ],
    [
      2.144054,
      "="
    ],
    [
      1.151775,
      "j"
    ],
    [
      0.200124,
      "a"
    ],
    [
      0.159750,
      "i"
    ],
    [
      0.440072,
      "1"
    ],
    [
      1.367919,
      "\u0008\u001b[K"
    ],
    [
      0.240020,
      "l"
    ],
    [
      0.407945,
      "1"
    ],
    [
      0.295996,
      " "
    ],
    [
      0.975923,
      "h"
    ],
    [
      0.063844,
      "o"
    ],
    [
      0.127976,
      "s"
    ],
    [
      0.256075,
      "t"
    ],
    [
      0.183956,
      "_"
    ],
    [
      0.375927,
      "h"
    ],
    [
      0.080001,
      "o"
    ],
    [
      0.088016,
      "s"
    ],
    [
      0.207958,
      "t"
    ],
    [
      0.087978,
      "n"
    ],
    [
      0.072032,
      "a"
    ],
    [
      0.111987,
      "m"
    ],
    [
      0.088030,
      "e"
    ],
    [
      0.928031,
      "="
    ],
    [
      0.095838,
      "e"
    ],
    [
      0.071185,
      "x"
    ],
    [
      0.224807,
      "a"
    ],
    [
      0.119770,
      "m"
    ],
    [
      0.184227,
      "p"
    ],
    [
      0.079800,
      "l"
    ],
    [
      0.112008,
      "e"
    ],
    [
      0.256184,
      "."
    ],
    [
      0.207738,
      "c"
    ],
    [
      0.119994,
      "o"
    ],
    [
      0.111823,
      "m"
    ],
    [
      0.312437,
      "\r\n"
    ],
    [
      0.051678,
      "\u001b[0;35mRename\u001b[0m"
    ],
    [
      0.376889,
      "\u001b[0;35m.\u001b[0m"
    ],
    [
      5.441859,
      "\u001b[0;32mok\u001b[0m\r\n"
    ],
    [
      0.001107,
      "[root@1-test-dtrace-01x /]# "
    ],
    [
      2.111676,
      "c"
    ],
    [
      0.375824,
      "b"
    ],
    [
      0.071995,
      "s"
    ],
    [
      0.087998,
      "d"
    ],
    [
      0.056023,
      " "
    ],
    [
      0.111986,
      "j"
    ],
    [
      0.071989,
      "l"
    ],
    [
      0.088037,
      "s"
    ],
    [
      0.255924,
      "\r\n"
    ],
    [
      0.061640,
      "\u001b[1mJNAME  JID  IP4_ADDR     HOST_HOSTNAME  PATH                    STATUS\u001b[0m\r\n\u001b[0mjail1  0    10.0.0.3/16  example.com    /usr/jails/jails/jail1  Off\r\n"
    ],
    [
      0.000995,
      "[root@1-test-dtrace-01x /]# "
    ],
    [
      1.969279,
      "exit\r\n"
    ]
  ]
}